{
  "name": "NFS-M8-QM-D2-N16 Sensor",
  "version": "1.0.0",
  "manufacturer": "Hilscher",
  "url": "https://www.hilscher.com/de/produkte/edge-gateways-mit-container-management/nfs-m8-qm-d2-n16-nfld",
  "description": "Hilschers sensorEDGE IO-Link Master.",
  "author": "Akenza AG",
  "comment": "Firmware Version, Loraddevice, Available Sensors, would all be empty",
  "firmwareVersion_notused": "V0.0.1",
  "loraDeviceClass_notused": "A",
  "availableSensors_notused": [
    "Humidity",
    "Temperature",
    "Button"
  ],
  "outputTopics": [
    "system_monitoring"
  ],
  "encoding": "JSON",
  "connectivity": "MQTT"
}