{
  "name": "ERS CO2",
  "version": "1.0.0",
  "manufacturer": "Elsys",
  "url": "https://www.elsys.se/en/ers-co2/",
  "description": "ERS CO2 gives you the opportunity to create the best possible workplace, classroom, library, or another public area. The sensor measures CO2, temperature, humidity, light, and motion.",
  "author": "Akenza AG",
  "firmwareVersion": "V2.3.5",
  "loraDeviceClass": "A",
  "availableSensors": ["Light", "Humidity", "Temperature", "CO2", "Motion"],
  "outputTopics": ["default", "lifecycle", "occupancy"],
  "encoding": "HEX",
  "connectivity": "LORA"
}
